{
  "tabPane": [
    {
      "title": "SmartDashboard",
      "autoPopulate": true,
      "autoPopulatePrefix": "SmartDashboard/",
      "widgetPane": {
        "gridSize": 128.0,
        "showGrid": true,
        "hgap": 16.0,
        "vgap": 16.0,
        "tiles": {
          "0,0": {
            "size": [
              1,
              1
            ],
            "content": {
              "_type": "Command",
              "_source0": "network_table:///SmartDashboard/Hood Auto",
              "_title": "Hood Auto"
            }
          },
          "1,0": {
            "size": [
              1,
              1
            ],
            "content": {
              "_type": "Command",
              "_source0": "network_table:///SmartDashboard/Hood Vision False",
              "_title": "Hood Vision False"
            }
          },
          "2,0": {
            "size": [
              1,
              1
            ],
            "content": {
              "_type": "Command",
              "_source0": "network_table:///SmartDashboard/Hood Close",
              "_title": "Hood Close"
            }
          },
          "3,0": {
            "size": [
              1,
              1
            ],
            "content": {
              "_type": "Command",
              "_source0": "network_table:///SmartDashboard/Reset Hood Position",
              "_title": "Reset Hood Position"
            }
          },
          "4,0": {
            "size": [
              1,
              1
            ],
            "content": {
              "_type": "Command",
              "_source0": "network_table:///SmartDashboard/Hood Vision True",
              "_title": "Hood Vision True"
            }
          },
          "5,0": {
            "size": [
              1,
              1
            ],
            "content": {
              "_type": "Text View",
              "_source0": "network_table:///SmartDashboard/odometry_theta",
              "_title": "odometry_theta"
            }
          },
          "6,0": {
            "size": [
              1,
              1
            ],
            "content": {
              "_type": "Command",
              "_source0": "network_table:///SmartDashboard/Hood Far",
              "_title": "Hood Far"
            }
          },
          "7,0": {
            "size": [
              1,
              1
            ],
            "content": {
              "_type": "Text View",
              "_source0": "network_table:///SmartDashboard/limelight_PipelineName",
              "_title": "limelight_PipelineName"
            }
          },
          "8,0": {
            "size": [
              1,
              1
            ],
            "content": {
              "_type": "Text View",
              "_source0": "network_table:///SmartDashboard/Shooter Hood Position",
              "_title": "Shooter Hood Position"
            }
          },
          "9,0": {
            "size": [
              1,
              1
            ],
            "content": {
              "_type": "Text View",
              "_source0": "network_table:///SmartDashboard/odometry_x",
              "_title": "odometry_x"
            }
          },
          "10,0": {
            "size": [
              1,
              1
            ],
            "content": {
              "_type": "Text View",
              "_source0": "network_table:///SmartDashboard/odometry_y",
              "_title": "odometry_y"
            }
          },
          "11,0": {
            "size": [
              1,
              1
            ],
            "content": {
              "_type": "Text View",
              "_source0": "network_table:///SmartDashboard/limelight_Interface",
              "_title": "limelight_Interface"
            }
          },
          "12,0": {
            "size": [
              1,
              1
            ],
            "content": {
              "_type": "Boolean Box",
              "_source0": "network_table:///SmartDashboard/button_close/running",
              "_title": "button_close/running",
              "Colors/Color when true": "#7CFC00FF",
              "Colors/Color when false": "#8B0000FF"
            }
          },
          "0,1": {
            "size": [
              1,
              1
            ],
            "content": {
              "_type": "ComboBox Chooser",
              "_source0": "network_table:///SmartDashboard/SendableChooser[2]",
              "_title": "SendableChooser[2]"
            }
          },
          "1,1": {
            "size": [
              1,
              1
            ],
            "content": {
              "_type": "Command",
              "_source0": "network_table:///SmartDashboard/Hood Manual",
              "_title": "Hood Manual"
            }
          },
          "2,1": {
            "size": [
              1,
              1
            ],
            "content": {
              "_type": "Text View",
              "_source0": "network_table:///SmartDashboard/Shooter A Power",
              "_title": "Shooter A Power"
            }
          },
          "3,1": {
            "size": [
              1,
              1
            ],
            "content": {
              "_type": "Text View",
              "_source0": "network_table:///SmartDashboard/ta",
              "_title": "ta"
            }
          },
          "4,1": {
            "size": [
              1,
              1
            ],
            "content": {
              "_type": "Text View",
              "_source0": "network_table:///SmartDashboard/ty",
              "_title": "ty"
            }
          },
          "5,1": {
            "size": [
              1,
              1
            ],
            "content": {
              "_type": "Text View",
              "_source0": "network_table:///SmartDashboard/tx",
              "_title": "tx"
            }
          },
          "6,1": {
            "size": [
              1,
              1
            ],
            "content": {
              "_type": "Text View",
              "_source0": "network_table:///SmartDashboard/Hood Set Point",
              "_title": "Hood Set Point"
            }
          },
          "7,1": {
            "size": [
              1,
              1
            ],
            "content": {
              "_type": "Text View",
              "_source0": "network_table:///SmartDashboard/left_enc",
              "_title": "left_enc"
            }
          },
          "8,1": {
            "size": [
              1,
              1
            ],
            "content": {
              "_type": "Boolean Box",
              "_source0": "network_table:///SmartDashboard/Hood Middle/running",
              "_title": "Hood Middle/running",
              "Colors/Color when true": "#7CFC00FF",
              "Colors/Color when false": "#8B0000FF"
            }
          },
          "9,1": {
            "size": [
              1,
              1
            ],
            "content": {
              "_type": "Text View",
              "_source0": "network_table:///SmartDashboard/right_enc",
              "_title": "right_enc"
            }
          },
          "10,1": {
            "size": [
              1,
              1
            ],
            "content": {
              "_type": "Text View",
              "_source0": "network_table:///SmartDashboard/Shooter B Current",
              "_title": "Shooter B Current"
            }
          },
          "11,1": {
            "size": [
              1,
              1
            ],
            "content": {
              "_type": "Text View",
              "_source0": "network_table:///SmartDashboard/Shooter B Power",
              "_title": "Shooter B Power"
            }
          },
          "12,1": {
            "size": [
              1,
              1
            ],
            "content": {
              "_type": "Text View",
              "_source0": "network_table:///SmartDashboard/Shooter Hood Current",
              "_title": "Shooter Hood Current"
            }
          },
          "0,2": {
            "size": [
              1,
              1
            ],
            "content": {
              "_type": "Text View",
              "_source0": "network_table:///SmartDashboard/Shooter Hood Voltage",
              "_title": "Shooter Hood Voltage"
            }
          },
          "1,2": {
            "size": [
              1,
              1
            ],
            "content": {
              "_type": "Text View",
              "_source0": "network_table:///SmartDashboard/limelight_Stream",
              "_title": "limelight_Stream"
            }
          },
          "0,3": {
            "size": [
              13,
              1
            ],
            "content": {
              "_type": "Number Slider",
              "_source0": "network_table:///SmartDashboard/LED Value",
              "_title": "LED Value",
              "Slider Settings/Min": -1.0,
              "Slider Settings/Max": 1.0,
              "Slider Settings/Block increment": 0.0625,
              "Visuals/Display value": true
            }
          },
          "3,2": {
            "size": [
              1,
              1
            ],
            "content": {
              "_type": "Text View",
              "_source0": "network_table:///SmartDashboard/Set Point",
              "_title": "Set Point"
            }
          },
          "4,2": {
            "size": [
              1,
              1
            ],
            "content": {
              "_type": "Text View",
              "_source0": "network_table:///SmartDashboard/Shooter A Current",
              "_title": "Shooter A Current"
            }
          },
          "2,2": {
            "size": [
              1,
              1
            ],
            "content": {
              "_type": "Text View",
              "_source0": "network_table:///SmartDashboard/BR_SP",
              "_title": "BR_SP"
            }
          },
          "5,2": {
            "size": [
              1,
              1
            ],
            "content": {
              "_type": "Text View",
              "_source0": "network_table:///SmartDashboard/FR_SP",
              "_title": "FR_SP"
            }
          },
          "6,2": {
            "size": [
              1,
              1
            ],
            "content": {
              "_type": "Text View",
              "_source0": "network_table:///SmartDashboard/D Gain",
              "_title": "D Gain"
            }
          },
          "7,2": {
            "size": [
              1,
              1
            ],
            "content": {
              "_type": "Text View",
              "_source0": "network_table:///SmartDashboard/I Zone",
              "_title": "I Zone"
            }
          },
          "8,2": {
            "size": [
              1,
              1
            ],
            "content": {
              "_type": "Text View",
              "_source0": "network_table:///SmartDashboard/P Gain",
              "_title": "P Gain"
            }
          },
          "9,2": {
            "size": [
              1,
              1
            ],
            "content": {
              "_type": "Text View",
              "_source0": "network_table:///SmartDashboard/Max Output",
              "_title": "Max Output"
            }
          },
          "10,2": {
            "size": [
              1,
              1
            ],
            "content": {
              "_type": "Text View",
              "_source0": "network_table:///SmartDashboard/BR_PV",
              "_title": "BR_PV"
            }
          },
          "11,2": {
            "size": [
              1,
              1
            ],
            "content": {
              "_type": "Text View",
              "_source0": "network_table:///SmartDashboard/FR_PV",
              "_title": "FR_PV"
            }
          },
          "12,2": {
            "size": [
              1,
              1
            ],
            "content": {
              "_type": "Text View",
              "_source0": "network_table:///SmartDashboard/BL_RawDrivespeed",
              "_title": "BL_RawDrivespeed"
            }
          },
          "0,4": {
            "size": [
              1,
              1
            ],
            "content": {
              "_type": "Text View",
              "_source0": "network_table:///SmartDashboard/FL_RawDrivespeed",
              "_title": "FL_RawDrivespeed"
            }
          },
          "1,4": {
            "size": [
              1,
              1
            ],
            "content": {
              "_type": "Text View",
              "_source0": "network_table:///SmartDashboard/I Gain",
              "_title": "I Gain"
            }
          },
          "2,4": {
            "size": [
              1,
              1
            ],
            "content": {
              "_type": "Text View",
              "_source0": "network_table:///SmartDashboard/BR_RawDrivespeed",
              "_title": "BR_RawDrivespeed"
            }
          },
          "3,4": {
            "size": [
              1,
              1
            ],
            "content": {
              "_type": "Text View",
              "_source0": "network_table:///SmartDashboard/FR_RawDrivespeed",
              "_title": "FR_RawDrivespeed"
            }
          },
          "4,4": {
            "size": [
              1,
              1
            ],
            "content": {
              "_type": "Text View",
              "_source0": "network_table:///SmartDashboard/BL_SP",
              "_title": "BL_SP"
            }
          },
          "5,4": {
            "size": [
              1,
              1
            ],
            "content": {
              "_type": "Text View",
              "_source0": "network_table:///SmartDashboard/FL_SP",
              "_title": "FL_SP"
            }
          },
          "6,4": {
            "size": [
              1,
              1
            ],
            "content": {
              "_type": "Text View",
              "_source0": "network_table:///SmartDashboard/BL_Speed",
              "_title": "BL_Speed"
            }
          },
          "7,4": {
            "size": [
              1,
              1
            ],
            "content": {
              "_type": "Text View",
              "_source0": "network_table:///SmartDashboard/FL_Speed",
              "_title": "FL_Speed"
            }
          },
          "8,4": {
            "size": [
              1,
              1
            ],
            "content": {
              "_type": "Text View",
              "_source0": "network_table:///SmartDashboard/BR_Speed",
              "_title": "BR_Speed"
            }
          },
          "9,4": {
            "size": [
              1,
              1
            ],
            "content": {
              "_type": "Text View",
              "_source0": "network_table:///SmartDashboard/FR_Speed",
              "_title": "FR_Speed"
            }
          },
          "10,4": {
            "size": [
              1,
              1
            ],
            "content": {
              "_type": "Text View",
              "_source0": "network_table:///SmartDashboard/BL_RawSteerSpeed",
              "_title": "BL_RawSteerSpeed"
            }
          },
          "11,4": {
            "size": [
              1,
              1
            ],
            "content": {
              "_type": "Text View",
              "_source0": "network_table:///SmartDashboard/FL_RawSteerSpeed",
              "_title": "FL_RawSteerSpeed"
            }
          },
          "12,4": {
            "size": [
              1,
              1
            ],
            "content": {
              "_type": "Text View",
              "_source0": "network_table:///SmartDashboard/BR_RawSteerSpeed",
              "_title": "BR_RawSteerSpeed"
            }
          },
          "0,5": {
            "size": [
              1,
              1
            ],
            "content": {
              "_type": "Text View",
              "_source0": "network_table:///SmartDashboard/BL_PV",
              "_title": "BL_PV"
            }
          },
          "1,5": {
            "size": [
              1,
              1
            ],
            "content": {
              "_type": "Text View",
              "_source0": "network_table:///SmartDashboard/BL_Angle",
              "_title": "BL_Angle"
            }
          },
          "2,5": {
            "size": [
              1,
              1
            ],
            "content": {
              "_type": "Text View",
              "_source0": "network_table:///SmartDashboard/Min Output",
              "_title": "Min Output"
            }
          },
          "3,5": {
            "size": [
              1,
              1
            ],
            "content": {
              "_type": "Text View",
              "_source0": "network_table:///SmartDashboard/FL_PV",
              "_title": "FL_PV"
            }
          },
          "4,5": {
            "size": [
              1,
              1
            ],
            "content": {
              "_type": "Text View",
              "_source0": "network_table:///SmartDashboard/FL_Angle",
              "_title": "FL_Angle"
            }
          },
          "5,5": {
            "size": [
              1,
              1
            ],
            "content": {
              "_type": "Text View",
              "_source0": "network_table:///SmartDashboard/BR_Angle",
              "_title": "BR_Angle"
            }
          },
          "6,5": {
            "size": [
              1,
              1
            ],
            "content": {
              "_type": "Text View",
              "_source0": "network_table:///SmartDashboard/FR_RawSteerSpeed",
              "_title": "FR_RawSteerSpeed"
            }
          },
          "7,5": {
            "size": [
              1,
              1
            ],
            "content": {
              "_type": "Text View",
              "_source0": "network_table:///SmartDashboard/FR_Angle",
              "_title": "FR_Angle"
            }
          },
          "8,5": {
            "size": [
              1,
              1
            ],
            "content": {
              "_type": "Text View",
              "_source0": "network_table:///SmartDashboard/Feed Forward",
              "_title": "Feed Forward"
            }
          },
          "9,5": {
            "size": [
              1,
              1
            ],
            "content": {
              "_type": "Text View",
              "_source0": "network_table:///SmartDashboard/m_x",
              "_title": "m_x"
            }
          },
          "10,5": {
            "size": [
              1,
              1
            ],
            "content": {
              "_type": "Text View",
              "_source0": "network_table:///SmartDashboard/m_y",
              "_title": "m_y"
            }
          },
          "11,5": {
            "size": [
              1,
              1
            ],
            "content": {
              "_type": "Text View",
              "_source0": "network_table:///SmartDashboard/m_twist",
              "_title": "m_twist"
            }
          }
        }
      }
    },
    {
      "title": "LiveWindow",
      "autoPopulate": true,
      "autoPopulatePrefix": "LiveWindow/",
      "widgetPane": {
        "gridSize": 128.0,
        "showGrid": true,
        "hgap": 16.0,
        "vgap": 16.0,
        "tiles": {
          "0,0": {
            "size": [
              2,
              4
            ],
            "content": {
              "_type": "Subsystem Layout",
              "_source0": "network_table:///LiveWindow/Climber",
              "_title": "Climber",
              "Layout/Label position": "BOTTOM",
              "_children": []
            }
          },
          "2,0": {
            "size": [
              2,
              4
            ],
            "content": {
              "_type": "Subsystem Layout",
              "_source0": "network_table:///LiveWindow/Ungrouped",
              "_title": "Ungrouped",
              "Layout/Label position": "BOTTOM",
              "_children": [
                {
                  "_type": "PID Controller",
                  "_source0": "network_table:///LiveWindow/Ungrouped/PIDController[1]",
                  "_title": "PIDController[1]"
                },
                {
                  "_type": "Gyro",
                  "_source0": "network_table:///LiveWindow/Ungrouped/ADXRS450_Gyro[0]",
                  "_title": "ADXRS450_Gyro[0]",
                  "Visuals/Major tick spacing": 45.0,
                  "Visuals/Starting angle": 180.0,
                  "Visuals/Show tick mark ring": true,
                  "Visuals/Counter clockwise": false
                },
                {
                  "_type": "Differential Drivebase",
                  "_source0": "network_table:///LiveWindow/Ungrouped/DifferentialDrive[1]",
                  "_title": "DifferentialDrive[1]",
                  "Wheels/Number of wheels": 4,
                  "Wheels/Wheel diameter": 80.0,
                  "Visuals/Show velocity vectors": true
                },
                {
                  "_type": "Speed Controller",
                  "_source0": "network_table:///LiveWindow/Ungrouped/VictorSP[2]",
                  "_title": "VictorSP[2]",
                  "Visuals/Orientation": "HORIZONTAL"
                },
                {
                  "_type": "PID Controller",
                  "_source0": "network_table:///LiveWindow/Ungrouped/PIDController[2]",
                  "_title": "PIDController[2]"
                },
                {
                  "_type": "Speed Controller",
                  "_source0": "network_table:///LiveWindow/Ungrouped/VictorSP[0]",
                  "_title": "VictorSP[0]",
                  "Visuals/Orientation": "HORIZONTAL"
                },
                {
                  "_type": "Speed Controller",
                  "_source0": "network_table:///LiveWindow/Ungrouped/Spark[1]",
                  "_title": "Spark[1]",
                  "Visuals/Orientation": "HORIZONTAL"
                },
                {
                  "_type": "Text View",
                  "_source0": "network_table:///LiveWindow/Ungrouped/DoubleSolenoid[0,2]/Value",
                  "_title": "DoubleSolenoid[0,2]/Value"
                },
                {
                  "_type": "Text View",
                  "_source0": "network_table:///LiveWindow/Ungrouped/DoubleSolenoid[0,0]/Value",
                  "_title": "DoubleSolenoid[0,0]/Value"
                }
              ]
            }
          },
          "4,0": {
            "size": [
              2,
              4
            ],
            "content": {
              "_type": "Subsystem Layout",
              "_source0": "network_table:///LiveWindow/Injector",
              "_title": "Injector",
              "Layout/Label position": "BOTTOM",
              "_children": []
            }
          },
          "6,0": {
            "size": [
              2,
              4
            ],
            "content": {
              "_type": "Subsystem Layout",
              "_source0": "network_table:///LiveWindow/VisionController",
              "_title": "VisionController",
              "Layout/Label position": "BOTTOM",
              "_children": []
            }
          },
          "8,0": {
            "size": [
              2,
              4
            ],
            "content": {
              "_type": "Subsystem Layout",
              "_source0": "network_table:///LiveWindow/LEDController",
              "_title": "LEDController",
              "Layout/Label position": "BOTTOM",
              "_children": []
            }
          },
          "10,0": {
            "size": [
              2,
              4
            ],
            "content": {
              "_type": "Subsystem Layout",
              "_source0": "network_table:///LiveWindow/ControlPanelManipulator",
              "_title": "ControlPanelManipulator",
              "Layout/Label position": "BOTTOM",
              "_children": []
            }
          }
        }
      }
    },
    {
      "title": "Tab 3",
      "autoPopulate": false,
      "autoPopulatePrefix": "",
      "widgetPane": {
        "gridSize": 96.0,
        "showGrid": true,
        "hgap": 12.0,
        "vgap": 12.0,
        "tiles": {
          "3,0": {
            "size": [
              2,
              1
            ],
            "content": {
              "_type": "Text View",
              "_source0": "network_table:///SmartDashboard/BL_Angle",
              "_title": "/SmartDashboard/BL_Angle"
            }
          },
          "3,1": {
            "size": [
              2,
              1
            ],
            "content": {
              "_type": "Text View",
              "_source0": "network_table:///SmartDashboard/BL_PV",
              "_title": "/SmartDashboard/BL_PV"
            }
          },
          "3,2": {
            "size": [
              2,
              1
            ],
            "content": {
              "_type": "Text View",
              "_source0": "network_table:///SmartDashboard/BL_RawDrivespeed",
              "_title": "/SmartDashboard/BL_RawDrivespeed"
            }
          },
          "3,3": {
            "size": [
              2,
              1
            ],
            "content": {
              "_type": "Text View",
              "_source0": "network_table:///SmartDashboard/BL_RawSteerSpeed",
              "_title": "/SmartDashboard/BL_RawSteerSpeed"
            }
          },
          "3,4": {
            "size": [
              2,
              1
            ],
            "content": {
              "_type": "Text View",
              "_source0": "network_table:///SmartDashboard/BL_SP",
              "_title": "/SmartDashboard/BL_SP"
            }
          },
          "3,5": {
            "size": [
              2,
              1
            ],
            "content": {
              "_type": "Text View",
              "_source0": "network_table:///SmartDashboard/BL_Speed",
              "_title": "/SmartDashboard/BL_Speed"
            }
          },
          "5,0": {
            "size": [
              2,
              1
            ],
            "content": {
              "_type": "Text View",
              "_source0": "network_table:///SmartDashboard/BR_Angle",
              "_title": "/SmartDashboard/BR_Angle"
            }
          },
          "5,1": {
            "size": [
              2,
              1
            ],
            "content": {
              "_type": "Text View",
              "_source0": "network_table:///SmartDashboard/BR_PV",
              "_title": "/SmartDashboard/BR_PV"
            }
          },
          "5,2": {
            "size": [
              2,
              1
            ],
            "content": {
              "_type": "Text View",
              "_source0": "network_table:///SmartDashboard/BR_RawDrivespeed",
              "_title": "/SmartDashboard/BR_RawDrivespeed"
            }
          },
          "5,3": {
            "size": [
              2,
              1
            ],
            "content": {
              "_type": "Text View",
              "_source0": "network_table:///SmartDashboard/BR_RawSteerSpeed",
              "_title": "/SmartDashboard/BR_RawSteerSpeed"
            }
          },
          "5,4": {
            "size": [
              2,
              1
            ],
            "content": {
              "_type": "Text View",
              "_source0": "network_table:///SmartDashboard/BR_SP",
              "_title": "/SmartDashboard/BR_SP"
            }
          },
          "5,5": {
            "size": [
              2,
              1
            ],
            "content": {
              "_type": "Text View",
              "_source0": "network_table:///SmartDashboard/BR_Speed",
              "_title": "/SmartDashboard/BR_Speed"
            }
          },
          "7,0": {
            "size": [
              2,
              1
            ],
            "content": {
              "_type": "Text View",
              "_source0": "network_table:///SmartDashboard/FL_Angle",
              "_title": "/SmartDashboard/FL_Angle"
            }
          },
          "7,1": {
            "size": [
              2,
              1
            ],
            "content": {
              "_type": "Text View",
              "_source0": "network_table:///SmartDashboard/FL_PV",
              "_title": "/SmartDashboard/FL_PV"
            }
          },
          "7,2": {
            "size": [
              2,
              1
            ],
            "content": {
              "_type": "Text View",
              "_source0": "network_table:///SmartDashboard/FL_RawDrivespeed",
              "_title": "/SmartDashboard/FL_RawDrivespeed"
            }
          },
          "7,3": {
            "size": [
              2,
              1
            ],
            "content": {
              "_type": "Text View",
              "_source0": "network_table:///SmartDashboard/FL_RawSteerSpeed",
              "_title": "/SmartDashboard/FL_RawSteerSpeed"
            }
          },
          "7,4": {
            "size": [
              2,
              1
            ],
            "content": {
              "_type": "Text View",
              "_source0": "network_table:///SmartDashboard/FL_SP",
              "_title": "/SmartDashboard/FL_SP"
            }
          },
          "7,5": {
            "size": [
              2,
              1
            ],
            "content": {
              "_type": "Text View",
              "_source0": "network_table:///SmartDashboard/FL_Speed",
              "_title": "/SmartDashboard/FL_Speed"
            }
          },
          "9,0": {
            "size": [
              2,
              1
            ],
            "content": {
              "_type": "Text View",
              "_source0": "network_table:///SmartDashboard/FR_Angle",
              "_title": "/SmartDashboard/FR_Angle"
            }
          },
          "9,1": {
            "size": [
              2,
              1
            ],
            "content": {
              "_type": "Text View",
              "_source0": "network_table:///SmartDashboard/FR_PV",
              "_title": "/SmartDashboard/FR_PV"
            }
          },
          "9,2": {
            "size": [
              2,
              1
            ],
            "content": {
              "_type": "Text View",
              "_source0": "network_table:///SmartDashboard/FR_RawDrivespeed",
              "_title": "/SmartDashboard/FR_RawDrivespeed"
            }
          },
          "9,3": {
            "size": [
              2,
              1
            ],
            "content": {
              "_type": "Text View",
              "_source0": "network_table:///SmartDashboard/FR_RawSteerSpeed",
              "_title": "/SmartDashboard/FR_RawSteerSpeed"
            }
          },
          "9,4": {
            "size": [
              2,
              1
            ],
            "content": {
              "_type": "Text View",
              "_source0": "network_table:///SmartDashboard/FR_SP",
              "_title": "/SmartDashboard/FR_SP"
            }
          },
          "9,5": {
            "size": [
              2,
              1
            ],
            "content": {
              "_type": "Text View",
              "_source0": "network_table:///SmartDashboard/FR_Speed",
              "_title": "/SmartDashboard/FR_Speed"
            }
          },
          "13,3": {
            "size": [
              2,
              1
            ],
            "content": {
              "_type": "Text View",
              "_source0": "network_table:///SmartDashboard/m_twist",
              "_title": "/SmartDashboard/m_twist"
            }
          },
          "13,4": {
            "size": [
              2,
              1
            ],
            "content": {
              "_type": "Text View",
              "_source0": "network_table:///SmartDashboard/m_x",
              "_title": "/SmartDashboard/m_x"
            }
          },
          "13,5": {
            "size": [
              2,
              1
            ],
            "content": {
              "_type": "Text View",
              "_source0": "network_table:///SmartDashboard/m_y",
              "_title": "/SmartDashboard/m_y"
            }
          }
        }
      }
    }
  ],
  "windowGeometry": {
    "x": 1912.0,
    "y": -8.0,
    "width": 1936.0,
    "height": 1066.0
  }
}